{
    "timestamp": "2025-10-24_01-54-55",
    "date_time": "October 24, 2025, 1:54 am",
    "student_id": "N\/A",
    "school_student_id": "2022-2-00448",
    "personal_info": {
        "first_name": null,
        "middle_name": "",
        "last_name": null,
        "university": "Lyceum of the Philippines University - Cavite"
    },
    "uploaded_file": "ID.jpg",
    "ocr_extraction": {
        "success": true,
        "method": "tesseract_multi_mode",
        "text_length": 158,
        "extracted_text": "@LPU\n\nLYCEUM OF THE PHILIPPINES UNIVERSITY\n\nCAVITE CAMPUS\n\neS\n\nA\n\neT\n\n+,\n\nfs\n\nf\n\nmel\n\npia\n\na:\n\n+ .\n\na\n\n\u2014\n\n\u201c\u00a5,\n\n\u00a2\n\na=\n\nSTUL\n\nta |All eae a\n\nvow\n\nRoyen |\n"
    },
    "validation_checks": {
        "first_name_match": {
            "passed": true,
            "similarity": 80,
            "threshold": 80,
            "expected": "Rojen",
            "found_in_ocr": true
        },
        "middle_name_match": {
            "passed": false,
            "similarity": 28.57,
            "threshold": 70,
            "expected": "Soliman",
            "found_in_ocr": false
        },
        "last_name_match": {
            "passed": false,
            "similarity": 28.57,
            "threshold": 80,
            "expected": "Soliman",
            "found_in_ocr": false
        },
        "university_match": {
            "passed": false,
            "similarity": 57.14,
            "threshold": 60,
            "expected": "Lyceum of the Philippines University - Cavite",
            "matched_words": "4\/7",
            "found_in_ocr": false
        },
        "document_keywords_found": {
            "passed": false,
            "found_count": 1,
            "required_count": 2,
            "total_keywords": 12,
            "found_keywords": [
                "university"
            ]
        },
        "school_student_id_match": {
            "passed": false,
            "similarity": 0,
            "threshold": 70,
            "expected": "2022-2-00448",
            "found_in_ocr": false,
            "note": "Not found - please verify"
        }
    },
    "confidence_scores": {
        "first_name": 80,
        "middle_name": 28.57,
        "last_name": 28.57,
        "university": 57.14285714285714,
        "keywords": 1,
        "school_student_id": 0,
        "average": 38.86
    },
    "overall_result": {
        "passed_checks": 1,
        "total_checks": 6,
        "recommendation": "Review - Please verify information matches your student ID",
        "status": "NEEDS REVIEW"
    }
}